README.md
setup.py
stac_tiler/__init__.py
stac_tiler/reader.py
stac_tiler/utils.py
stac_tiler.egg-info/PKG-INFO
stac_tiler.egg-info/SOURCES.txt
stac_tiler.egg-info/dependency_links.txt
stac_tiler.egg-info/not-zip-safe
stac_tiler.egg-info/requires.txt
stac_tiler.egg-info/top_level.txt