Metadata-Version: 2.1
Name: stac-tiler
Version: 0.0rc2
Summary: A rio-tiler plugin to handle STAC items
Home-page: https://github.com/developmentseed/stac-tiler
Author: Vincent Sarago
Author-email: vincent@developmentseed.org
License: MIT
Keywords: COG STAC GIS
Platform: UNKNOWN
Classifier: Intended Audience :: Information Technology
Classifier: Intended Audience :: Science/Research
Classifier: License :: OSI Approved :: BSD License
Classifier: Programming Language :: Python :: 3.6
Classifier: Programming Language :: Python :: 3.7
Classifier: Topic :: Scientific/Engineering :: GIS
Requires-Python: >=3
Provides-Extra: dev
Provides-Extra: test
